Shp2ncmask/__S2NParams.py
Shp2ncmask/__curses_doc.py
Shp2ncmask/__doc.py
Shp2ncmask/__exceptions.py
Shp2ncmask/__exec.py
Shp2ncmask/__grid.py
Shp2ncmask/__init__.py
Shp2ncmask/__inputs.py
Shp2ncmask/__logs.py
Shp2ncmask/__mask.py
Shp2ncmask/__plot.py
Shp2ncmask/__release.py
shp2ncmask-2.1.2.data/scripts/shp2ncmask
shp2ncmask-2.1.2.dist-info/LICENSE
shp2ncmask-2.1.2.dist-info/METADATA
shp2ncmask-2.1.2.dist-info/WHEEL
shp2ncmask-2.1.2.dist-info/top_level.txt
shp2ncmask-2.1.2.dist-info/RECORD
